exercicio-3-13 (Gray sem FFD)/exercicio-3-13.v
module contador_gray(input clk, rst, output [4:0] cont);
    reg [4:0] cont_aux;
    reg bit1 = 1'b1; // 0 [1] (2 estados, aguarda o segundo)
    reg [1:0] bit2 = 2'b10; // 0 1 [10] 11 (4 estados, aguarda o terceiro)
    reg [2:0] bit3 = 3'b100; // 0 1 10 11 [100] 101 110 111 (8 estados, aguarda o quarto)
    reg [3:0] bit4 = 4'b1000; // 0 1 10 11 100 101 110 111 [1000] 1001 1001 1011 1100 1101 1110 1111 (16 estados, aguarda o oitavo)
    reg [4:0] bit5 = 5'b10000; // Mesma lógica

    initial begin
        $display("[ffd] Circuito Contador Gray carregado.");
    end

    always @(negedge(clk) or posedge rst)
    begin
        if (rst == 1'b1)
            begin
                $display("[ffd] Reset Acionado.");

                cont_aux = 5'b00000;
                bit1 = 1'b1; // 0 [1] (2 estados, aguarda o segundo)
                bit2 = 2'b10; // 0 1 [10] 11 (4 estados, aguarda o terceiro)
                bit3 = 3'b100; // 0 1 10 11 [100] 101 110 111 (8 estados, aguarda o quarto)
                bit4 = 4'b1000; // 0 1 10 11 100 101 110 111 [1000] 1001 1001 1011 1100 1101 1110 1111 (16 estados, aguarda o oitavo)
                bit5 = 5'b10000;
            end
        else if (clk == 1'b0)
            begin
                $display("[ffd] Borda de descida detectada! RST = %b | bit1 = %b | bit2 = %b | bit3 = %b | bit4 = %b | bit5 = %b", rst, bit1, bit2, bit3, bit4, bit5);

                if (bit1 == 1'b0) // Se rodou, troca. Se não, mantém.
                    cont_aux[0] = ~cont_aux[0];
                if (bit2 == 2'b00)
                    cont_aux[1] = ~cont_aux[1];
                if (bit3 == 3'b000)
                    cont_aux[2] = ~cont_aux[2];
                if (bit4 == 4'b0000)
                    cont_aux[3] = ~cont_aux[3];
                if (bit5 == 5'b00000)
                    cont_aux[4] = ~cont_aux[4];

                bit1 <= bit1 + 1;
                bit2 <= bit2 + 1;
                bit3 <= bit3 + 1;
                bit4 <= bit4 + 1;
                bit5 <= bit5 + 1;

                $display("[ffd] Novo Valor: cont = %b", cont_aux);
            end        
    end
    
    assign cont = cont_aux;
endmodule

/*
Contador Gray:

00000
00001
00011
00010
00110
00111
00101
00100

1 bit -> 1x0, 2x1, 2x0, 2x1, ...
2 bit -> 2x0, 4x1, 4x0, 4x1, ...
3 bit -> 4x0, 8x1, 8x0, 8x1, ...
4 bit -> 8x0, 16x1, 16x0, 16x1, ...

Eu montei registradores que guardam essa alternância de estados. Como o primeiro sempre inicia na metade da transição sempre com zeros, já inicializo eles manualmente.
*/

exercicio-3-13 (Gray sem FFD)/exercicio-3-13_tb.v
`include "exercicio-3-13.v"

// ==========================================
// 2. O SIMULADOR (MÓDULO TESTBENCH)
// ==========================================
`timescale 1ns/1ns // Unidade de tempo / Precisão de tempo (5.001 funciona)

module contador_gray_tb;
    // Definindo como reg para armazenar estados passados 
    reg clk = 0;
    reg rst;
    // Definindo como wire pois são controladas pelo flip-flop, não pelo testbench
    wire [5:0] cont;

    // Criando uma instância/cópia do circuito dentro do simulador
    contador_gray uut (
        .clk(clk), 
        .rst(rst), 
        .cont(cont)
    );

    // Faz o clock oscilar de 5 em 5 nanosegundos de forma infinita
    always #5 clk = ~clk;

    initial begin
        $dumpfile("resultado.vcd"); // Cria o arquivo de ondas (que salva a simulação inteira, até o $finish)
        $dumpvars(0, contador_gray_tb);       // Salva as variáveis do teste

        $display("[Teste] Começou a simulação!");
        
        // Inicializa os sinais
        $display("[Teste] Dando Reset, esperando 10ns");
        rst = 1; // Liga o reset
        #10;     // Espera passar 12ns
        
        $display("[Teste] Desligando Reset e rodando por 100ns (10 pulsos de clock)");
        rst = 0; // Desliga o reset
        #100;     // Espera passar 10ns (vai pegar uma borda de descida aqui)
        
        $display("[Teste] Fim da simulação.");
        $finish; // IMPORTANTE: Para o relógio do simulador, senão ele roda eterno
    end
endmodule

exercicio-3-13 (Gray sem FFD)/resultado.vcd
$date
	Fri Jun 19 01:40:49 2026
$end
$version
	Icarus Verilog
$end
$timescale
	1ns
$end
$scope module contador_gray_tb $end
$var wire 6 ! cont [5:0] $end
$var reg 1 " clk $end
$var reg 1 # rst $end
$scope module uut $end
$var wire 1 " clk $end
$var wire 1 # rst $end
$var wire 5 $ cont [4:0] $end
$var reg 1 % bit1 $end
$var reg 2 & bit2 [1:0] $end
$var reg 3 ' bit3 [2:0] $end
$var reg 4 ( bit4 [3:0] $end
$var reg 5 ) bit5 [4:0] $end
$var reg 5 * cont_aux [4:0] $end
$upscope $end
$upscope $end
$enddefinitions $end
$comment Show the parameter values. $end
$dumpall
$end
#0
$dumpvars
b0 *
b10000 )
b1000 (
b100 '
b10 &
1%
b0 $
1#
0"
b0 !
$end
#5
1"
#10
b10001 )
b1001 (
b101 '
b11 &
0%
0"
0#
#15
1"
#20
b10010 )
b1010 (
b110 '
b0 &
1%
b1 !
b1 $
b1 *
0"
#25
1"
#30
b10011 )
b1011 (
b111 '
b1 &
0%
b11 !
b11 $
b11 *
0"
#35
1"
#40
b10100 )
b1100 (
b0 '
b10 &
1%
b10 !
b10 $
b10 *
0"
#45
1"
#50
b10101 )
b1101 (
b1 '
b11 &
0%
b110 !
b110 $
b110 *
0"
#55
1"
#60
b10110 )
b1110 (
b10 '
b0 &
1%
b111 !
b111 $
b111 *
0"
#65
1"
#70
b10111 )
b1111 (
b11 '
b1 &
0%
b101 !
b101 $
b101 *
0"
#75
1"
#80
b11000 )
b0 (
b100 '
b10 &
1%
b100 !
b100 $
b100 *
0"
#85
1"
#90
b11001 )
b1 (
b101 '
b11 &
0%
b1100 !
b1100 $
b1100 *
0"
#95
1"
#100
b11010 )
b10 (
b110 '
b0 &
1%
b1101 !
b1101 $
b1101 *
0"
