exercicio-3-14 (Bidi FFD)/exercicio-3-14.v
// FLIP FLOP D COM RESET
module FFD(input D, clk, rst, output Qb, output reg Q);
    initial begin
        $display("[ffd] Circuito FFD carregado.");
    end

    always @(posedge clk)
    begin
        if (rst == 1'b1) begin
            $display("[ffd] Reset detectado.");
            Q <= 1'b0;
        end
        else begin
            //$display("[ffd] Aplicando D = %b.", D);
            Q <= D;
        end
        
        //$strobe("[ffd] Borda de subida detectada! RST = %b | D = %b | Q = %b", rst, D, Q);
    end

    assign Qb = ~Q;
endmodule

// Deslocador Bidirecional
module deslocador_bidirecional(input serial_input, clk, right, rst, output [4:0] Q);
    wire [4:0] D; // Wire: Recebe atribuições contínuas (assign). Se for reg, não tem como "soldar".
    wire [4:0] Qb;

    // Assign: "soldando entradas" com portas lógicas.
    assign D[0] = (serial_input && right) || (~right && Q[1]);
    assign D[1] = (Q[0] && right) || (~right && Q[2]);
    assign D[2] = (Q[1] && right) || (~right && Q[3]);
    assign D[3] = (Q[2] && right) || (~right && Q[4]);
    assign D[4] = (Q[3] && right) || (~right && serial_input);

    // Dando os fios para os inputs do flip flop.
    FFD ffd0 (.D(D[0]), .clk(clk), .rst(rst), .Qb(Qb[0]), .Q(Q[0]));
    FFD ffd1 (.D(D[1]), .clk(clk), .rst(rst), .Qb(Qb[1]), .Q(Q[1]));
    FFD ffd2 (.D(D[2]), .clk(clk), .rst(rst), .Qb(Qb[2]), .Q(Q[2]));
    FFD ffd3 (.D(D[3]), .clk(clk), .rst(rst), .Qb(Qb[3]), .Q(Q[3]));
    FFD ffd4 (.D(D[4]), .clk(clk), .rst(rst), .Qb(Qb[4]), .Q(Q[4]));

    initial begin
        $display("[Desl Bid] Circuito Deslocador Bidirecional carregado.");
    end

    always @(posedge(clk) or posedge(rst))
    begin
        $display("[Desl Bid] Valor atual: %b", Q);
    end
endmodule

/*
ANOTAÇÕES

Com clock, tudo que tem always roda em paralelo.
*/

exercicio-3-14 (Bidi FFD)/exercicio-3-14_tb.v
`include "exercicio-3-14.v"

// ==========================================
// 2. O SIMULADOR (MÓDULO TESTBENCH)
// ==========================================
`timescale 1ns/1ns // Unidade de tempo / Precisão de tempo (5.001 funciona)

module deslocador_bidirecional_tb;
    // Definindo como reg para armazenar estados passados 
    reg clk = 0;
    reg rst = 0;
    reg serial_input;
    reg right = 1;
    wire [4:0] out;

    // Criando uma instância/cópia do circuito dentro do simulador
    deslocador_bidirecional uut (
        .clk(clk), 
        .rst(rst), 
        .serial_input(serial_input),
        .right(right),
        .Q(out)
    );

    // Faz o clock oscilar de 5 em 5 nanosegundos de forma infinita
    always #5 clk = ~clk;

    initial begin
        $dumpfile("resultado.vcd"); // Cria o arquivo de ondas (que salva a simulação inteira, até o $finish)
        $dumpvars(0, deslocador_bidirecional_tb);       // Salva as variáveis do teste

        $display("[Teste] Começou a simulação!");
        
        // Inicializa os sinais
        $display("[Teste] Dando Reset, esperando 10ns");
        rst = 1; // Liga o reset
        #10;     // Espera passar 10ns
        
        $display("[Teste] Desligando Reset, Emitindo 1 no Serial Input, com Right = 1 e esperando 10ns");
        rst = 0;
        serial_input = 1;
        right = 1;
        #10;
        $display("[Teste] Rodando por 40ns (4 pulsos de clock)");
        serial_input = 0;
        #40;
        $display("[Teste] Invertendo e rodando por 40ns (4 pulsos de clock)");
        right = 0;
        #40;
        
        $display("[Teste] Fim da simulação.");
        $finish; // IMPORTANTE: Para o relógio do simulador, senão ele roda eterno
    end
endmodule

exercicio-3-14 (Bidi FFD)/resultado.vcd
$date
	Fri Jun 19 18:03:57 2026
$end
$version
	Icarus Verilog
$end
$timescale
	1ns
$end
$scope module deslocador_bidirecional_tb $end
$var wire 5 ! out [4:0] $end
$var reg 1 " clk $end
$var reg 1 # right $end
$var reg 1 $ rst $end
$var reg 1 % serial_input $end
$scope module uut $end
$var wire 1 " clk $end
$var wire 1 # right $end
$var wire 1 $ rst $end
$var wire 1 % serial_input $end
$var wire 5 & Qb [4:0] $end
$var wire 5 ' Q [4:0] $end
$var wire 5 ( D [4:0] $end
$scope module ffd0 $end
$var wire 1 ) D $end
$var wire 1 * Qb $end
$var wire 1 " clk $end
$var wire 1 $ rst $end
$var reg 1 + Q $end
$upscope $end
$scope module ffd1 $end
$var wire 1 , D $end
$var wire 1 - Qb $end
$var wire 1 " clk $end
$var wire 1 $ rst $end
$var reg 1 . Q $end
$upscope $end
$scope module ffd2 $end
$var wire 1 / D $end
$var wire 1 0 Qb $end
$var wire 1 " clk $end
$var wire 1 $ rst $end
$var reg 1 1 Q $end
$upscope $end
$scope module ffd3 $end
$var wire 1 2 D $end
$var wire 1 3 Qb $end
$var wire 1 " clk $end
$var wire 1 $ rst $end
$var reg 1 4 Q $end
$upscope $end
$scope module ffd4 $end
$var wire 1 5 D $end
$var wire 1 6 Qb $end
$var wire 1 " clk $end
$var wire 1 $ rst $end
$var reg 1 7 Q $end
$upscope $end
$upscope $end
$upscope $end
$enddefinitions $end
$comment Show the parameter values. $end
$dumpall
$end
#0
$dumpvars
x7
x6
x5
x4
x3
x2
x1
x0
x/
x.
x-
x,
x+
x*
x)
bx (
bx '
bx &
x%
1$
1#
0"
bx !
$end
#5
0,
0/
02
05
b0x (
b11111 &
b0 !
b0 '
1*
1-
10
13
16
0+
0.
01
04
07
1"
#10
1)
b1 (
0"
1%
0$
#15
1,
b11 (
b11110 &
b1 !
b1 '
0*
1+
1"
#20
0)
b10 (
0"
0%
#25
0,
1/
b100 (
b11101 &
b10 !
b10 '
1*
0-
0+
1.
1"
#30
0"
#35
0/
12
b1000 (
b11011 &
b100 !
b100 '
00
1-
11
0.
1"
#40
0"
#45
02
15
b10000 (
b10111 &
b1000 !
b1000 '
10
03
01
14
1"
#50
0"
#55
05
b0 (
b1111 &
b10000 !
b10000 '
06
13
17
04
1"
#60
12
b1000 (
0"
0#
#65
1/
02
b100 (
b10111 &
b1000 !
b1000 '
03
16
14
07
1"
#70
0"
#75
1,
0/
b10 (
b11011 &
b100 !
b100 '
13
00
04
11
1"
#80
0"
#85
1)
0,
b1 (
b11101 &
b10 !
b10 '
0-
10
1.
01
1"
#90
0"
#95
0)
b0 (
b11110 &
b1 !
b1 '
1-
0*
0.
1+
1"
