exercicio-3-12 (Johnson sem FFD)/exercicio-3-12.v
module contador_johson(input clk, rst, output [4:0] cont);
    reg [4:0] cont_aux;

    initial begin
        $display("[ffd] Circuito Contador Johnson carregado.");
    end

    always @(negedge(clk) or posedge(rst))
    begin
        if (rst == 1'b1)
            begin
                cont_aux = 5'b10000; // Precisa voltar pra 10000 (se não fica preso em 0 pra sempre)
            end
        else if (clk == 1'b0)
            begin
                cont_aux = {~cont_aux[0], cont_aux[4:1]};
            end
        
        $strobe("[ffd] Borda de descida detectada! RST = %b | cont = %b", rst, cont_aux);
    end

    assign cont = cont_aux;
endmodule

/*
Contador Johnson:

000
001
011
111
110
100
000
*/

exercicio-3-12 (Johnson sem FFD)/exercicio-3-12_tb.v
`include "exercicio-3-12.v"

// ==========================================
// 2. O SIMULADOR (MÓDULO TESTBENCH)
// ==========================================
`timescale 1ns/1ns // Unidade de tempo / Precisão de tempo (5.001 funciona)

module contador_johson_tb;
    // Definindo como reg para armazenar estados passados 
    reg clk = 0;
    reg rst;
    // Definindo como wire pois são controladas pelo flip-flop, não pelo testbench
    wire [4:0] cont;

    // Criando uma instância/cópia do circuito dentro do simulador
    contador_johson uut (
        .clk(clk), 
        .rst(rst), 
        .cont(cont)
    );

    // Faz o clock oscilar de 5 em 5 nanosegundos de forma infinita
    always #5 clk = ~clk;

    initial begin
        $dumpfile("resultado.vcd"); // Cria o arquivo de ondas (que salva a simulação inteira, até o $finish)
        $dumpvars(0, contador_johson_tb);       // Salva as variáveis do teste

        $display("[Teste] Começou a simulação!");
        
        // Inicializa os sinais
        $display("[Teste] Dando Reset, esperando 10ns");
        rst = 1; // Liga o reset
        #10;     // Espera passar 12ns
        
        $display("[Teste] Desligando Reset e rodando por 100ns (10 pulsos de clock)");
        rst = 0; // Desliga o reset
        #100;     // Espera passar 10ns (vai pegar uma borda de descida aqui)
        
        $display("[Teste] Fim da simulação.");
        $finish; // IMPORTANTE: Para o relógio do simulador, senão ele roda eterno
    end
endmodule

exercicio-3-12 (Johnson sem FFD)/resultado.vcd
$date
	Fri Jun 19 00:34:17 2026
$end
$version
	Icarus Verilog
$end
$timescale
	1ns
$end
$scope module contador_johson_tb $end
$var wire 5 ! cont [4:0] $end
$var reg 1 " clk $end
$var reg 1 # rst $end
$scope module uut $end
$var wire 1 " clk $end
$var wire 5 $ cont [4:0] $end
$var wire 1 # rst $end
$var reg 5 % cont_aux [4:0] $end
$upscope $end
$upscope $end
$enddefinitions $end
$comment Show the parameter values. $end
$dumpall
$end
#0
$dumpvars
b10000 %
b10000 $
1#
0"
b10000 !
$end
#5
1"
#10
b11000 !
b11000 $
b11000 %
0"
0#
#15
1"
#20
b11100 !
b11100 $
b11100 %
0"
#25
1"
#30
b11110 !
b11110 $
b11110 %
0"
#35
1"
#40
b11111 !
b11111 $
b11111 %
0"
#45
1"
#50
b1111 !
b1111 $
b1111 %
0"
#55
1"
#60
b111 !
b111 $
b111 %
0"
#65
1"
#70
b11 !
b11 $
b11 %
0"
#75
1"
#80
b1 !
b1 $
b1 %
0"
#85
1"
#90
b0 !
b0 $
b0 %
0"
#95
1"
#100
b10000 !
b10000 $
b10000 %
0"
#105
1"
#110
b11000 !
b11000 $
b11000 %
0"
