exercicio-3-12 (Johnson FFD)/exercicio-3-12.v
// FLIP FLOP D COM RESET
module FFD(input D, clk, rst, output Qb, output reg Q);
    initial begin
        $display("[ffd] Circuito FFD carregado.");
    end

    always @(posedge clk)
    begin
        if (rst == 1'b1) begin
            $display("[ffd] Reset detectado.");
            Q <= 1'b0;
        end
        else begin
            //$display("[ffd] Aplicando D = %b.", D);
            Q <= D;
        end
        
        //$strobe("[ffd] Borda de subida detectada! RST = %b | D = %b | Q = %b", rst, D, Q);
    end

    assign Qb = ~Q;
endmodule

// Deslocador Bidirecional
module contador_johnson(input clk, rst, output [4:0] Q);
    wire [4:0] D; // Wire: Recebe atribuições contínuas (assign). Se for reg, não tem como "soldar".
    wire [4:0] Qb;

    // Assign: "soldando entradas" com portas lógicas.
    assign D[0] = ~Q[4];
    assign D[1] = Q[0];
    assign D[2] = Q[1];
    assign D[3] = Q[2];
    assign D[4] = Q[3];

    // Dando os fios para os inputs do flip flop.
    FFD ffd0 (.D(D[0]), .clk(clk), .rst(rst), .Qb(Qb[0]), .Q(Q[0]));
    FFD ffd1 (.D(D[1]), .clk(clk), .rst(rst), .Qb(Qb[1]), .Q(Q[1]));
    FFD ffd2 (.D(D[2]), .clk(clk), .rst(rst), .Qb(Qb[2]), .Q(Q[2]));
    FFD ffd3 (.D(D[3]), .clk(clk), .rst(rst), .Qb(Qb[3]), .Q(Q[3]));
    FFD ffd4 (.D(D[4]), .clk(clk), .rst(rst), .Qb(Qb[4]), .Q(Q[4]));

    initial begin
        $display("[Cont. John] Circuito Contador Johnson carregado.");
    end

    always @(posedge(clk) or posedge(rst))
    begin
        $display("[Cont. John] Valor atual: %b", Q);
    end
endmodule

/*
ANOTAÇÕES

Com clock, tudo que tem always roda em paralelo.
*/

exercicio-3-12 (Johnson FFD)/exercicio-3-12_tb.v
`include "./exercicio-3-12.v"

// ==========================================
// 2. O SIMULADOR (MÓDULO TESTBENCH)
// ==========================================
`timescale 1ns/1ns // Unidade de tempo / Precisão de tempo (5.001 funciona)

module contador_johnson_tb;
    // Definindo como reg para armazenar estados passados 
    reg clk = 0;
    reg rst = 0;
    wire [4:0] out;

    // Criando uma instância/cópia do circuito dentro do simulador
    contador_johnson uut (
        .clk(clk), 
        .rst(rst), 
        .Q(out)
    );

    // Faz o clock oscilar de 5 em 5 nanosegundos de forma infinita
    always #5 clk = ~clk;

    initial begin
        $dumpfile("resultado.vcd"); // Cria o arquivo de ondas (que salva a simulação inteira, até o $finish)
        $dumpvars(0, contador_johnson_tb);       // Salva as variáveis do teste

        $display("[Teste] Começou a simulação!");
        
        // Inicializa os sinais
        $display("[Teste] Dando Reset, esperando 10ns");
        rst = 1; // Liga o reset
        #10;     // Espera passar 10ns
        
        $display("[Teste] Desligando Reset e esperando 10ns");
        rst = 0;
        #10;
        $display("[Teste] Rodando por 100ns (10 pulsos de clock)");
        #100;
        
        $display("[Teste] Fim da simulação.");
        $finish; // IMPORTANTE: Para o relógio do simulador, senão ele roda eterno
    end
endmodule

exercicio-3-12 (Johnson FFD)/resultado.vcd
$date
	Fri Jun 19 18:09:01 2026
$end
$version
	Icarus Verilog
$end
$timescale
	1ns
$end
$scope module contador_johnson_tb $end
$var wire 5 ! out [4:0] $end
$var reg 1 " clk $end
$var reg 1 # rst $end
$scope module uut $end
$var wire 1 " clk $end
$var wire 1 # rst $end
$var wire 5 $ Qb [4:0] $end
$var wire 5 % Q [4:0] $end
$var wire 5 & D [4:0] $end
$scope module ffd0 $end
$var wire 1 ' D $end
$var wire 1 ( Qb $end
$var wire 1 " clk $end
$var wire 1 # rst $end
$var reg 1 ) Q $end
$upscope $end
$scope module ffd1 $end
$var wire 1 * D $end
$var wire 1 + Qb $end
$var wire 1 " clk $end
$var wire 1 # rst $end
$var reg 1 , Q $end
$upscope $end
$scope module ffd2 $end
$var wire 1 - D $end
$var wire 1 . Qb $end
$var wire 1 " clk $end
$var wire 1 # rst $end
$var reg 1 / Q $end
$upscope $end
$scope module ffd3 $end
$var wire 1 0 D $end
$var wire 1 1 Qb $end
$var wire 1 " clk $end
$var wire 1 # rst $end
$var reg 1 2 Q $end
$upscope $end
$scope module ffd4 $end
$var wire 1 3 D $end
$var wire 1 4 Qb $end
$var wire 1 " clk $end
$var wire 1 # rst $end
$var reg 1 5 Q $end
$upscope $end
$upscope $end
$upscope $end
$enddefinitions $end
$comment Show the parameter values. $end
$dumpall
$end
#0
$dumpvars
x5
x4
x3
x2
x1
x0
x/
x.
x-
x,
x+
x*
x)
x(
x'
bx &
bx %
bx $
1#
0"
bx !
$end
#5
1'
0*
0-
00
03
b1 &
b11111 $
b0 !
b0 %
1(
1+
1.
11
14
0)
0,
0/
02
05
1"
#10
0"
0#
#15
1*
b11 &
b11110 $
b1 !
b1 %
0(
1)
1"
#20
0"
#25
1-
b111 &
b11100 $
b11 !
b11 %
0+
1,
1"
#30
0"
#35
10
b1111 &
b11000 $
b111 !
b111 %
0.
1/
1"
#40
0"
#45
13
b11111 &
b10000 $
b1111 !
b1111 %
01
12
1"
#50
0"
#55
0'
b11110 &
b0 $
b11111 !
b11111 %
04
15
1"
#60
0"
#65
0*
b11100 &
b1 $
b11110 !
b11110 %
1(
0)
1"
#70
0"
#75
0-
b11000 &
b11 $
b11100 !
b11100 %
1+
0,
1"
#80
0"
#85
00
b10000 &
b111 $
b11000 !
b11000 %
1.
0/
1"
#90
0"
#95
03
b0 &
b1111 $
b10000 !
b10000 %
11
02
1"
#100
0"
#105
1'
b1 &
b11111 $
b0 !
b0 %
14
05
1"
#110
0"
#115
1*
b11 &
b11110 $
b1 !
b1 %
0(
1)
1"
